termbrowser/__init__.py
termbrowser/adom.py
termbrowser/browser.py
termbrowser/pieces.py
termbrowser/render.py
termbrowser/term.py
termbrowser/term2doc.py
termbrowser/util.py
termbrowser/vector.py
termbrowser/window.py
termbrowser/local/welcome.term
termbrowser-0.1.7.data/scripts/term
termbrowser-0.1.7.data/scripts/term.py
termbrowser-0.1.7.dist-info/LICENSE
termbrowser-0.1.7.dist-info/METADATA
termbrowser-0.1.7.dist-info/WHEEL
termbrowser-0.1.7.dist-info/top_level.txt
termbrowser-0.1.7.dist-info/RECORD
