Metadata-Version: 2.1
Name: termbrowser
Version: 0.1.7
Summary: Terminal web browser.
Home-page: https://github.com/Jaggler3/term
Author: Martin Darazs
Author-email: martin.protostar@gmail.com
License: MIT
Platform: UNKNOWN
Classifier: License :: OSI Approved :: MIT License
Classifier: Programming Language :: Python
Classifier: Programming Language :: Python :: 3
Classifier: Programming Language :: Python :: 3.6
Classifier: Programming Language :: Python :: Implementation :: CPython
Classifier: Programming Language :: Python :: Implementation :: PyPy
Requires-Python: >=3.6.0
Requires-Dist: requests
Requires-Dist: simpleeval
Requires-Dist: pyperclip
